test_project_pycon2021/__init__.py
test_project_pycon2021/__main__.py
test_project_pycon2021-0.0.2.data/scripts/hello
test_project_pycon2021-0.0.2.dist-info/METADATA
test_project_pycon2021-0.0.2.dist-info/WHEEL
test_project_pycon2021-0.0.2.dist-info/entry_points.txt
test_project_pycon2021-0.0.2.dist-info/top_level.txt
test_project_pycon2021-0.0.2.dist-info/RECORD
