Metadata-Version: 2.1
Name: test-project-pycon2021
Version: 0.0.2
Summary: A demo of Sailboat's capabilities
Home-page: https://github.com
Author: Cole Wilson
Author-email: cole@colewilson.xyz
License: none
Keywords: kw1 kw2 kw3
Platform: UNKNOWN
Classifier: Programming Language :: Python :: 3
Requires-Python: >=3.6
